{
    "gender": {
        "male": "16.67%",
        "female": "83.33%"
    },
    "age": [
        {
            "range": "0-19",
            "percent": "25.00%"
        },
        {
            "range": "20-29",
            "percent": "50.00%"
        },
        {
            "range": "30-39",
            "percent": "23.00%"
        },
        {
            "range": "40-49",
            "percent": "25.00%"
        },
        {
            "range": "50+",
            "percent": "2.00%"
        }
    ],
    "summary": {
        "total_in": {
            "count": 5,
            "change": "100%"
        },
        "total_out": {
            "count": 1,
            "change": "100%"
        },
        "total_visitors": {
            "count": 6,
            "change": "100%"
        }
    },
    "graph": [
        {
            "date": "2025-03-19",
            "hour": "00:00",
            "in": 5,
            "out": 10
        },
        {
            "date": "2025-03-19",
            "hour": "00:30",
            "in": 0,
            "out": 0
        },
        {
            "date": "2025-03-19",
            "hour": "01:00",
            "in": 0,
            "out": 0
        },
        {
            "date": "2025-03-19",
            "hour": "01:30",
            "in": 0,
            "out": 0
        },
        {
            "date": "2025-03-19",
            "hour": "02:00",
            "in": 0,
            "out": 0
        },
        {
            "date": "2025-03-19",
            "hour": "02:30",
            "in": 0,
            "out": 0
        },
        {
            "date": "2025-03-19",
            "hour": "03:00",
            "in": 0,
            "out": 0
        },
        {
            "date": "2025-03-19",
            "hour": "03:30",
            "in": 0,
            "out": 0
        },
        {
            "date": "2025-03-19",
            "hour": "04:00",
            "in": 0,
            "out": 0
        },
        {
            "date": "2025-03-19",
            "hour": "04:30",
            "in": 0,
            "out": 0
        },
        {
            "date": "2025-03-19",
            "hour": "05:00",
            "in": 30,
            "out": 20
        },
        {
            "date": "2025-03-19",
            "hour": "05:30",
            "in": 25,
            "out": 20
        },
        {
            "date": "2025-03-19",
            "hour": "06:00",
            "in": 22,
            "out": 16
        },
        {
            "date": "2025-03-19",
            "hour": "06:30",
            "in": 0,
            "out": 0
        },
        {
            "date": "2025-03-19",
            "hour": "07:00",
            "in": 5,
            "out": 6
        },
        {
            "date": "2025-03-19",
            "hour": "07:30",
            "in": 0,
            "out": 0
        },
        {
            "date": "2025-03-19",
            "hour": "08:00",
            "in": 0,
            "out": 0
        },
        {
            "date": "2025-03-19",
            "hour": "08:30",
            "in": 0,
            "out": 0
        },
        {
            "date": "2025-03-19",
            "hour": "09:00",
            "in": 45,
            "out": 54
        },
        {
            "date": "2025-03-19",
            "hour": "09:30",
            "in": 0,
            "out": 0
        },
        {
            "date": "2025-03-19",
            "hour": "10:00",
            "in": 0,
            "out": 0
        },
        {
            "date": "2025-03-19",
            "hour": "10:30",
            "in": 0,
            "out": 0
        },
        {
            "date": "2025-03-19",
            "hour": "11:00",
            "in": 0,
            "out": 0
        },
        {
            "date": "2025-03-19",
            "hour": "11:30",
            "in": 0,
            "out": 0
        },
        {
            "date": "2025-03-19",
            "hour": "12:00",
            "in": 0,
            "out": 0
        },
        {
            "date": "2025-03-19",
            "hour": "12:30",
            "in": 0,
            "out": 0
        },
        {
            "date": "2025-03-19",
            "hour": "13:00",
            "in": 0,
            "out": 0
        },
        {
            "date": "2025-03-19",
            "hour": "13:30",
            "in": 0,
            "out": 0
        },
        {
            "date": "2025-03-19",
            "hour": "14:00",
            "in": 40,
            "out": 32
        },
        {
            "date": "2025-03-19",
            "hour": "14:30",
            "in": 45,
            "out": 23
        },
        {
            "date": "2025-03-19",
            "hour": "15:00",
            "in": 0,
            "out": 0
        },
        {
            "date": "2025-03-19",
            "hour": "15:30",
            "in": 0,
            "out": 0
        },
        {
            "date": "2025-03-19",
            "hour": "16:00",
            "in": 0,
            "out": 0
        },
        {
            "date": "2025-03-19",
            "hour": "16:30",
            "in": 0,
            "out": 0
        },
        {
            "date": "2025-03-19",
            "hour": "17:00",
            "in": 0,
            "out": 0
        },
        {
            "date": "2025-03-19",
            "hour": "17:30",
            "in": 0,
            "out": 0
        },
       
            { "date": "2025-03-19", "hour": "18:00", "in": 5, "out": 2 },
            { "date": "2025-03-19", "hour": "18:30", "in": 8, "out": 4 },
            { "date": "2025-03-19", "hour": "19:00", "in": 3, "out": 1 },
            { "date": "2025-03-19", "hour": "19:30", "in": 6, "out": 3 },
            { "date": "2025-03-19", "hour": "20:00", "in": 7, "out": 5 },
            { "date": "2025-03-19", "hour": "20:30", "in": 10, "out": 7 },
            { "date": "2025-03-19", "hour": "21:00", "in": 12, "out": 9 },
            { "date": "2025-03-19", "hour": "21:30", "in": 9, "out": 11 },
            { "date": "2025-03-19", "hour": "22:00", "in": 4, "out": 6 },
            { "date": "2025-03-19", "hour": "22:30", "in": 2, "out": 3 },
            { "date": "2025-03-19", "hour": "23:00", "in": 1, "out": 2 },
            { "date": "2025-03-19", "hour": "23:30", "in": 0, "out": 1 }
                    
    ]
}